dreamfinetune/__init__.py
dreamfinetune/trainings/Inpaint.py
dreamfinetune/trainings/TextToImage.py
dreamfinetune/trainings/__init__.py
dreamfinetune/utils/DreamBoothDataset.py
dreamfinetune/utils/PromptDataset.py
dreamfinetune/utils/__init__.py
dreamfinetune-1.5.dist-info/LICENSE
dreamfinetune-1.5.dist-info/METADATA
dreamfinetune-1.5.dist-info/WHEEL
dreamfinetune-1.5.dist-info/dependency_links.txt
dreamfinetune-1.5.dist-info/top_level.txt
dreamfinetune-1.5.dist-info/RECORD
