Metadata-Version: 2.1
Name: dreamfinetune
Version: 1.5
Home-page: https://github.com/skillfi/fine-tuning
Author: Alex
License: Apache 2.0 License
Classifier: Development Status :: 5 - Production/Stable
Classifier: Intended Audience :: Developers
Classifier: Intended Audience :: Education
Classifier: Intended Audience :: Science/Research
Classifier: License :: OSI Approved :: Apache Software License
Classifier: Operating System :: OS Independent
Classifier: Topic :: Scientific/Engineering :: Artificial Intelligence
Classifier: Programming Language :: Python :: 3
Classifier: Programming Language :: Python :: 3.8
Classifier: Programming Language :: Python :: 3.9
Classifier: Programming Language :: Python :: 3.10
Classifier: Programming Language :: Python :: 3.11
Classifier: Programming Language :: Python :: 3.12
Requires-Python: >=3.8
License-File: LICENSE
Requires-Dist: pillow>=9.4.0
Requires-Dist: diffusers~=0.30.0
Requires-Dist: transformers<4.45.0,>=4.42.4
Requires-Dist: tqdm~=4.66.4
Requires-Dist: datasets~=2.20.0
Requires-Dist: bitsandbytes
Requires-Dist: ftfy
Requires-Dist: gradio
Requires-Dist: tensorboard
Provides-Extra: torch
Requires-Dist: torch>=2.3.1; extra == "torch"
Requires-Dist: torchvision>=0.18.0; extra == "torch"
Requires-Dist: torchaudio>=2.3.1; extra == "torch"
